an_multithreadsmanager/__init__.py
an_multithreadsmanager/multithreadsmanager.py
an_multithreadsmanager-0.3.4.dist-info/licenses/LICENSE
an_multithreadsmanager-0.3.4.dist-info/METADATA
an_multithreadsmanager-0.3.4.dist-info/WHEEL
an_multithreadsmanager-0.3.4.dist-info/top_level.txt
an_multithreadsmanager-0.3.4.dist-info/RECORD
