Metadata-Version: 2.4
Name: an_multithreadsmanager
Version: 0.3.4
Summary: A package for an_multithreadsmanager.
Home-page: https://github.com/Atsushi888/Atsushi888
Author: Atsushi888
Author-email: Atsushi888 <vtgrotxu@gmail.com>
Project-URL: Homepage, https://github.com/Atsushi888/an_multithreadsmanager
Project-URL: Repository, https://github.com/Atsushi888/an_multithreadsmanager
Requires-Python: >=3.6
License-File: LICENSE
Requires-Dist: an_DebugHelper
Dynamic: author
Dynamic: home-page
Dynamic: license-file
Dynamic: requires-python
